gribtoarrow/__init__.py
gribtoarrow/eccodes/libeccodes.so
gribtoarrow/eccodes/libeccodes_memfs.so
gribtoarrow/gribtoarrow.cpython-39-x86_64-linux-gnu.so
gribtoarrow/lib/libaec.so
gribtoarrow/lib/libaec.so.0
gribtoarrow/lib/libaec.so.0.1.2
gribtoarrow/lib/libeccodes_memfs.so
gribtoarrow/lib/libsz.so
gribtoarrow/lib/libsz.so.2
gribtoarrow/lib/libsz.so.2.0.1
gribtoarrow.cpython-39-x86_64-linux-gnu.so
gribtoarrow-0.1.13.dist-info/METADATA
gribtoarrow-0.1.13.dist-info/WHEEL
gribtoarrow-0.1.13.dist-info/RECORD
