Metadata-Version: 2.1
Name: gribtoarrow
Version: 0.1.13
Summary: gribtoarrow is a python module to export data in the GRIB format to Apache Arrow
Author: Hugo Pendlebury
Requires-Python: >=3.9,<4.0
Classifier: Programming Language :: Python :: 3
Classifier: Programming Language :: Python :: 3.9
Classifier: Programming Language :: Python :: 3.10
Classifier: Programming Language :: Python :: 3.11
Classifier: Programming Language :: Python :: 3.12
Requires-Dist: cmake (>=3.28.1,<4.0.0)
Requires-Dist: pyarrow (>=14.0.2,<15.0.0)
Requires-Dist: pybind11 (>=2.11.1,<3.0.0)
Requires-Dist: pybind11-stubgen (>=2.4.2,<3.0.0)
